quant_lens/__init__.py
quant_lens/core.py
quant_lens/geometry.py
quant_lens/hessian.py
quant_lens/plotting.py
quant_lens/quantization.py
quant_lens-0.1.0.dist-info/licenses/LICENSE
quant_lens-0.1.0.dist-info/METADATA
quant_lens-0.1.0.dist-info/WHEEL
quant_lens-0.1.0.dist-info/top_level.txt
quant_lens-0.1.0.dist-info/RECORD
