Metadata-Version: 2.4
Name: quant-lens
Version: 0.1.0
Summary: Zero-dependency quantization diagnostic toolkit for neural networks
Author-email: Sairam S <saisr2206@gmail.com>
License: MIT
Project-URL: Homepage, https://github.com/s-sairam/quant-lens
Project-URL: Documentation, https://github.com/s-sairam/quant-lens/blob/main/README.md
Project-URL: Repository, https://github.com/s-sairam/quant-lens
Project-URL: Bug Tracker, https://github.com/s-sairam/quant-lens/issues
Keywords: quantization,neural networks,loss landscape,hessian,diagnostics
Classifier: Development Status :: 4 - Beta
Classifier: Intended Audience :: Science/Research
Classifier: Intended Audience :: Developers
Classifier: License :: OSI Approved :: MIT License
Classifier: Programming Language :: Python :: 3
Classifier: Programming Language :: Python :: 3.8
Classifier: Programming Language :: Python :: 3.9
Classifier: Programming Language :: Python :: 3.10
Classifier: Programming Language :: Python :: 3.11
Classifier: Topic :: Scientific/Engineering :: Artificial Intelligence
Classifier: Topic :: Software Development :: Libraries :: Python Modules
Requires-Python: >=3.8
License-File: LICENSE
Requires-Dist: torch>=2.0.0
Requires-Dist: numpy>=1.20.0
Requires-Dist: matplotlib>=3.5.0
Provides-Extra: dev
Requires-Dist: pytest>=7.0; extra == "dev"
Requires-Dist: black>=22.0; extra == "dev"
Requires-Dist: flake8>=4.0; extra == "dev"
Requires-Dist: mypy>=0.950; extra == "dev"
Dynamic: license-file
